devlacruz_hashlib-0.1.6.dist-info/METADATA
devlacruz_hashlib-0.1.6.dist-info/WHEEL
devlacruz_hashlib-0.1.6.dist-info/licenses/LICENSE
devlacruz_hashlib/__init__.py
devlacruz_hashlib/devlacruz_hashlib.cp312-win_amd64.pyd
devlacruz_hashlib-0.1.6.dist-info/RECORD
