Metadata-Version: 2.4
Name: devlacruz_hashlib
Version: 0.1.6
Classifier: Programming Language :: Python :: 3
Classifier: Programming Language :: Python :: 3.8
Classifier: Programming Language :: Python :: 3.9
Classifier: Programming Language :: Python :: 3.10
Classifier: Programming Language :: Python :: 3.11
Classifier: Programming Language :: Python :: 3.12
Classifier: Programming Language :: Python :: 3.13
Classifier: Programming Language :: Rust
Classifier: License :: OSI Approved :: MIT License
Classifier: Operating System :: OS Independent
Classifier: Topic :: Security :: Cryptography
License-File: LICENSE
Summary: Extensión de hashing SHA-256 acelerado con Rust y PyO3
Author-email: Alejandro De La Cruz <devlacruz@axtosys.com>
License: MIT
Requires-Python: >=3.8, <4.0
Project-URL: Source Code, https://github.com/DevLaCruz/devlacruz_hashlib
